kamalsql/__init__.py
kamalsql/kamalsql.py
kamalsql-1.0.0.dist-info/LICENSE
kamalsql-1.0.0.dist-info/METADATA
kamalsql-1.0.0.dist-info/WHEEL
kamalsql-1.0.0.dist-info/top_level.txt
kamalsql-1.0.0.dist-info/RECORD
