Metadata-Version: 2.1
Name: kamalsql
Version: 1.0.0
Summary: A simple Python wrapper for your MySQL needs.
Home-page: https://github.com/KamalDGRT/kamalsql
Author: Kamal Sharma
Author-email: kamaldgrt@gmail.com
License: MIT
Keywords: Simple,Functional,Dependable
Platform: UNKNOWN
Classifier: Development Status :: 1 - Planning
Classifier: Intended Audience :: Developers
Classifier: Natural Language :: English
Classifier: Topic :: Software Development :: Libraries :: Python Modules
Classifier: Topic :: Database
Classifier: Topic :: Software Development :: Libraries
Classifier: License :: OSI Approved :: MIT License
Classifier: Programming Language :: Python :: 3
License-File: LICENSE
Requires-Dist: mysql-connector
Requires-Dist: tabulate
